alpha_parser/__init__.py
alpha_parser/alpha_lexer.py
alpha_parser/alpha_parser.py
alpha_parser/lexer.py
alpha_parser/parser.py
alpha_parser/test_alphas.py
alpha_parser/tokens.py
alpha_parser-0.1.2.dist-info/licenses/LICENSE
alpha_parser-0.1.2.dist-info/METADATA
alpha_parser-0.1.2.dist-info/WHEEL
alpha_parser-0.1.2.dist-info/top_level.txt
alpha_parser-0.1.2.dist-info/RECORD
