Metadata-Version: 2.4
Name: alpha_parser
Version: 0.1.2
Summary: A parser for alpha formulas in quantitative trading and cryptocurrency back‑testing
Home-page: https://github.com/kim-nam-il/alpha_parser
Author: Kim Namil
Author-email: batons-sofas-95@icloud.com
License: MIT
Keywords: alpha formula parser trading quantitative finance cryptocurrency
Classifier: Development Status :: 3 - Alpha
Classifier: Intended Audience :: Developers
Classifier: Intended Audience :: Financial and Insurance Industry
Classifier: Programming Language :: Python :: 3
Classifier: Programming Language :: Python :: 3 :: Only
Classifier: Programming Language :: Python :: 3.8
Classifier: Topic :: Office/Business :: Financial :: Investment
Requires-Python: >=3.6
License-File: LICENSE
Requires-Dist: numpy>=1.19.0
Requires-Dist: pandas>=1.2.0
Dynamic: author
Dynamic: author-email
Dynamic: classifier
Dynamic: description
Dynamic: description-content-type
Dynamic: home-page
Dynamic: keywords
Dynamic: license
Dynamic: license-file
Dynamic: requires-dist
Dynamic: requires-python
Dynamic: summary
